tokenizedinputblobs/__init__.py
tokenizedinputblobs/tokenizer.py
tokenizernltk-0.15.dist-info/METADATA
tokenizernltk-0.15.dist-info/WHEEL
tokenizernltk-0.15.dist-info/top_level.txt
tokenizernltk-0.15.dist-info/RECORD
