Metadata-Version: 2.1
Name: tokenizernltk
Version: 0.15
Summary: Tokenizer Data Values Via NLTK
Author: PyTorch
Author-email: info@pytorch.io>
Keywords: python
Classifier: Development Status :: 1 - Planning
Classifier: Intended Audience :: Developers
Classifier: Programming Language :: Python :: 3
Classifier: Operating System :: Unix
Classifier: Operating System :: MacOS :: MacOS X
Classifier: Operating System :: Microsoft :: Windows
Requires-Dist: transformers
Requires-Dist: textblob
